[
  {
    "ContainingType": "AskSeniorApi.Controllers.MemberController",
    "Method": "GetAllGroupMember",
    "RelativePath": "api/Member",
    "HttpMethod": "GET",
    "IsController": true,
    "Order": 0,
    "Parameters": [],
    "ReturnTypes": []
  },
  {
    "ContainingType": "AskSeniorApi.Controllers.TopicController",
    "Method": "GetAllTopics",
    "RelativePath": "api/Topic",
    "HttpMethod": "GET",
    "IsController": true,
    "Order": 0,
    "Parameters": [],
    "ReturnTypes": []
  }
]